<?xml version="1.0" encoding="utf-8" ?> 
<wordList>
  <category id="0">
    <name>Biology</name>
    <words>
      <word>
        <name>Bob</name>
        <hint>Its not Bob</hint>
      </word>
      <word>
        <name>Bill</name>
        <hint>Its not Bill</hint>
      </word>
      <word>
        <name>Bill The Angel</name>
        <hint>Its not Bill</hint>
      </word>
      <word>
        <name>Sam</name>
        <hint>Its not Sam</hint>
      </word>
    </words>
  </category>
  <category id="1">
    <name>Chemistry</name>
    <words>
      <word>
        <name>Clint</name>
        <hint>Its not Clint</hint>
      </word>
    </words>
  </category>
  <category id="2">
    <name>Phsyics</name>
    <words>
      <word>
        <name>Da-ve</name>
        <hint>Its not Dave</hint>
      </word>
    </words>
  </category>
 </wordList>